{
    "Embed": {
        "Title": "TableTop - Geek & Sundry",
        "Description": "[Тайм-код](https://youtu.be/X9QtdiRJYro?t=840)```:turnedoutright:```\nНуу... ничего сделать нельзя, так сложилось. Сложилось в мою пользу! Мухаха.",
        "URL": "https://www.youtube.com/channel/UCaBf1a-dpIsw8OxqH4ki2Kg",
        "Color": "#76bc1e",
        "TimeStamp": 1555638182803
    },
    "UniqueID": 14,
    "Position": 12,
    "EmojiName": "turnedoutright",
    "MessageHash": "2b677b37552aea54edc13fdae9de75f3",
    "MessageID": "568717094980681740",
    "ImageHash": "e994953ad18227282fcc6b76451c361a"
}